tangy-0.9.2.dist-info/RECORD
tangy-0.9.2.dist-info/WHEEL
tangy-0.9.2.dist-info/entry_points.txt
tangy-0.9.2.dist-info/top_level.txt
tangy-0.9.2.dist-info/METADATA
tangy-0.9.2.dist-info/licenses/LICENSE
tangy_src/src/vector_impls.h
tangy_src/src/tangy.h
tangy_src/src/analysis_impl_standard.h
tangy_src/src/analysis_impl_clocked.h
tangy_src/src/shared_memory.c
tangy_src/src/shared_ring_buffer_context.h
tangy_src/src/qutools_reader.h
tangy_src/src/picoquant_reader.h
tangy_src/src/base.h
tangy/__init__.py
tangy/py.typed
tangy/_tangy.cpython-311-darwin.so
tangy/apps/gui_uqd.py
tangy/apps/__init__.py
tangy/apps/gui_coincidence_counter.py
