Metadata-Version: 2.4
Name: tangy
Version: 0.9.2
Summary: Timetag analysing library
Author-email: Peter Thomas Barrow <peter.barrow.93@gmail.com>
Maintainer-email: Peter Thomas Barrow <peter.barrow.93@gmail.com>
Project-URL: Homepage, https://github.com/Peter-Barrow/tangy
Project-URL: Repository, https://github.com/Peter-Barrow/tangy.git
Project-URL: Issues, https://github.com/Peter-Barrow/tangy/issues
License-File: LICENSE
Requires-Dist: numpy>=2.0.0
Requires-Dist: scipy
Requires-Dist: platformdirs
Requires-Dist: customtkinter
Provides-Extra: gui
Requires-Dist: customtkinter; extra == "gui"
Provides-Extra: docs
Requires-Dist: mkdocs; extra == "docs"
Requires-Dist: mkdocs-material; extra == "docs"
Requires-Dist: mkdocstrings; extra == "docs"
Requires-Dist: mkdocs-jupyter; extra == "docs"
Requires-Dist: mkdoxy; extra == "docs"
Dynamic: license-file
